LICENSE.txt
MANIFEST.in
setup.cfg
setup.py
contrib/el_aap
contrib/el_aap.ini
contrib/el_aap_api
contrib/el_aap_api.ini
contrib/el_aap_cli
el_aap/__init__.py
el_aap/app.py
el_aap.egg-info/PKG-INFO
el_aap.egg-info/SOURCES.txt
el_aap.egg-info/dependency_links.txt
el_aap.egg-info/requires.txt
el_aap.egg-info/top_level.txt
el_aap/controllers/__init__.py
el_aap/controllers/cluster_api.py
el_aap/controllers/document_api.py
el_aap/controllers/index_api.py
el_aap/controllers/plugins_api.py
el_aap/controllers/search_api.py
el_aap/models/__init__.py
el_aap/models/aa.py
el_aap/models/elproxy.py
el_aap_api/__init__.py
el_aap_api/app.py
el_aap_api/errors.py
el_aap_api/schemas.py
el_aap_api/controllers/__init__.py
el_aap_api/controllers/authenticate.py
el_aap_api/controllers/permissions.py
el_aap_api/controllers/roles.py
el_aap_api/controllers/static.py
el_aap_api/controllers/users.py
el_aap_api/models/__init__.py
el_aap_api/models/aa.py
el_aap_api/models/lostpw.py
el_aap_api/models/mixins.py
el_aap_api/models/permissions.py
el_aap_api/models/roles.py
el_aap_api/models/session.py
el_aap_api/models/users.py
el_aap_cli/__init__.py
static/swagger/index.html
static/swagger/o2c.html
static/swagger/swagger-ui.js
static/swagger/swagger-ui.min.js
static/swagger/css/print.css
static/swagger/css/reset.css
static/swagger/css/screen.css
static/swagger/css/style.css
static/swagger/css/typography.css
static/swagger/fonts/DroidSans-Bold.ttf
static/swagger/fonts/DroidSans.ttf
static/swagger/images/explorer_icons.png
static/swagger/images/favicon-16x16.png
static/swagger/images/favicon-32x32.png
static/swagger/images/favicon.ico
static/swagger/images/logo_small.png
static/swagger/images/pet_store_api.png
static/swagger/images/throbber.gif
static/swagger/images/wordnik_api.png
static/swagger/lang/en.js
static/swagger/lang/es.js
static/swagger/lang/fr.js
static/swagger/lang/it.js
static/swagger/lang/ja.js
static/swagger/lang/pt.js
static/swagger/lang/ru.js
static/swagger/lang/tr.js
static/swagger/lang/translator.js
static/swagger/lang/zh-cn.js
static/swagger/lib/backbone-min.js
static/swagger/lib/handlebars-2.0.0.js
