Metadata-Version: 1.1
Name: el-aap
Version: 0.0.13
Summary: Elasticsearch Authentication and Authorization Proxy
Home-page: https://github.com/schlitzered/pyredis
Author: schlitzer
Author-email: stephan.schultchen@gmail.com
License: MIT
Keywords: elasticsearch
Platform: posix
Classifier: License :: OSI Approved :: MIT License
Classifier: Programming Language :: Python :: 3
